pytest_pinned.py
pytest_pinned-0.4.2.dist-info/LICENSE
pytest_pinned-0.4.2.dist-info/METADATA
pytest_pinned-0.4.2.dist-info/WHEEL
pytest_pinned-0.4.2.dist-info/entry_points.txt
pytest_pinned-0.4.2.dist-info/top_level.txt
pytest_pinned-0.4.2.dist-info/RECORD
