Metadata-Version: 2.1
Name: pytest-pinned
Version: 0.4.2
Summary: A simple pytest plugin for pinning tests
Home-page: https://github.com/freol35241/pytest-pinned
Author: Fredrik Olsson
Author-email: freol@outlook.com
Maintainer: Fredrik Olsson
Maintainer-email: freol@outlook.com
License: MIT
Platform: UNKNOWN
Classifier: Development Status :: 4 - Beta
Classifier: Framework :: Pytest
Classifier: Topic :: Software Development :: Testing
Classifier: Programming Language :: Python :: 3.5
Classifier: Programming Language :: Python :: 3.6
Classifier: Programming Language :: Python :: 3.7
Classifier: Programming Language :: Python :: 3.8
Classifier: Operating System :: OS Independent
Classifier: License :: OSI Approved :: MIT License
Requires-Python: >=3.5
License-File: LICENSE
Requires-Dist: pytest (>=3.5.0)
